neuronswitch/__init__.py
neuronswitch/farida_DualConv.py
neuronswitch/farida_DualYOLO.py
neuronswitch-2.0.4.dist-info/licenses/LICENSE
neuronswitch-2.0.4.dist-info/METADATA
neuronswitch-2.0.4.dist-info/WHEEL
neuronswitch-2.0.4.dist-info/top_level.txt
neuronswitch-2.0.4.dist-info/RECORD
