Metadata-Version: 2.4
Name: neuronswitch
Version: 2.0.4
Summary: Dual-model detection for YOLO backbones
Author-email: Shreyas Potdar <shreyasapp9@gmail.com>
Maintainer-email: Shreyas Potdar <shreyasapp9@gmail.com>
License-Expression: Apache-2.0
Project-URL: Homepage, https://github.com/SHREYAS1188/neuronswitch
Project-URL: Source, https://github.com/SHREYAS1188/neuronswitch
Keywords: yolo,opencv,keras,cv2,performence
Classifier: Development Status :: 5 - Production/Stable
Classifier: Intended Audience :: Developers
Classifier: Operating System :: OS Independent
Classifier: Programming Language :: Python :: 3
Classifier: Programming Language :: Python :: 3.6
Classifier: Programming Language :: Python :: 3.7
Classifier: Programming Language :: Python :: 3.8
Classifier: Programming Language :: Python :: 3.9
Classifier: Programming Language :: Python :: 3.10
Classifier: Programming Language :: Python :: 3.11
Classifier: Programming Language :: Python :: 3.12
Classifier: Programming Language :: Python :: 3.13
Classifier: Programming Language :: Python :: 3 :: Only
Requires-Python: >=3.6
License-File: LICENSE
Requires-Dist: torch
Requires-Dist: ultralytics
Dynamic: license-file
